spark_tensorflow_distributor/__init__.py
spark_tensorflow_distributor/mirrored_strategy_runner.py
spark_tensorflow_distributor-1.0.0.dist-info/METADATA
spark_tensorflow_distributor-1.0.0.dist-info/WHEEL
spark_tensorflow_distributor-1.0.0.dist-info/top_level.txt
spark_tensorflow_distributor-1.0.0.dist-info/RECORD
