Metadata-Version: 2.1
Name: spark-tensorflow-distributor
Version: 1.0.0
Summary: This package helps users do distributed training with TensorFlow on their Spark clusters.
Home-page: https://github.com/tensorflow/ecosystem/tree/master/spark/spark-tensorflow-distributor
Author: sarthfrey
Author-email: sarth.frey@gmail.com
License: UNKNOWN
Platform: UNKNOWN
Classifier: Development Status :: 1 - Planning
Classifier: Intended Audience :: Developers
Classifier: Operating System :: OS Independent
Classifier: Programming Language :: Python :: 3
Classifier: Natural Language :: English
Classifier: Topic :: Scientific/Engineering :: Artificial Intelligence
Classifier: Topic :: Software Development :: Libraries :: Python Modules
Classifier: Topic :: Software Development :: Version Control :: Git
Requires-Python: >=3.6
